pychee6/__init__.py
pychee6/cli.py
pychee6/pychee6.py
pychee6/rm_title_des.py
pychee6/locales/zh_CN/LC_MESSAGES/zh_CN.mo
pychee6/locales/zh_CN/LC_MESSAGES/zh_CN.po
pychee6-0.4.7.dist-info/METADATA
pychee6-0.4.7.dist-info/WHEEL
pychee6-0.4.7.dist-info/top_level.txt
pychee6-0.4.7.dist-info/RECORD
