Metadata-Version: 2.4
Name: pychee6
Version: 0.4.7
Summary: A simple python moudle for Lychee
Home-page: https://github.com/x1ntt/pychee6
Author: x1nt
Author-email: cjdty@qq.com
Requires-Dist: requests
Requires-Dist: termcolor
Dynamic: author
Dynamic: author-email
Dynamic: description
Dynamic: description-content-type
Dynamic: home-page
Dynamic: requires-dist
Dynamic: summary
